netkiller_kindle-0.0.2.data/data/etc/kindle.ini
netkiller_kindle-0.0.2.data/scripts/kindle
src/__init__.py
netkiller_kindle-0.0.2.dist-info/LICENSE
netkiller_kindle-0.0.2.dist-info/METADATA
netkiller_kindle-0.0.2.dist-info/WHEEL
netkiller_kindle-0.0.2.dist-info/top_level.txt
netkiller_kindle-0.0.2.dist-info/RECORD
