Metadata-Version: 2.1
Name: netkiller-kindle
Version: 0.0.2
Summary: Send ebook to kindle device
Home-page: http://netkiller.github.io
Author: Neo Chen
Author-email: netkiller@msn.com
License: MIT
Download-URL: https://github.com/netkiller/kindle
Keywords: kindle
Platform: UNKNOWN
Classifier: Environment :: Console
Classifier: Intended Audience :: Developers
Classifier: License :: OSI Approved :: MIT License
Classifier: Operating System :: OS Independent
Classifier: Programming Language :: Python
Classifier: Programming Language :: Python :: 3
